{
  "loadouts": [
    {
      "name": "Loadout 1",
      "loadoutItems": {
        "weapons": [
          {
            "name": "Grau 5.56",
            "type": "Primary",
            "image": "./weapons/Grau_556.png",
            "attachments": [
              {
                "category": "Muzzle",
                "name": "Tactical Suppressor",
                "image": "./attachments/muzzle/tacticalSuppressor.png"
              },
              {
                "category": "Optic",
                "name": "Integral Hibrida",
                "image": "./attachments/optic/integralHybrid.png"
              },
              {
                "category": "Underbarrel",
                "name": "Comando Foregrip",
                "image": "./attachments/underbarrel/comandoForegrip.png"
              },
              {
                "category": "Ammunition",
                "name": "60 Round Mags",
                "image": "./attachments/ammunition/60roundMags.png"
              },
              {
                "category": "Perks",
                "name": "Sleight Of Hand",
                "image": "./attachments/perk/sleightOfHand.png"
              }
            ]
          },
          {
            "name": "MP7",
            "type": "Secundary",
            "image": "./weapons/MP7.png",
            "attachments": [
              {
                "category": "Muzzle",
                "name": "Tactical Suppressor",
                "image": "./attachments/muzzle/tacticalSuppressor.png"
              },
              {
                "category": "Optic",
                "name": "Integral Hibrida",
                "image": "./attachments/optic/integralHybrid.png"
              },
              {
                "category": "Underbarrel",
                "name": "Comando Foregrip",
                "image": "./attachments/underbarrel/comandoForegrip.png"
              },
              {
                "category": "Ammunition",
                "name": "60 Round Mags",
                "image": "./attachments/ammunition/60roundMags.png"
              },
              {
                "category": "Perks",
                "name": "Sleight Of Hand",
                "image": "./attachments/perk/sleightOfHand.png"
              }
            ]
          }
        ],
        "perks": [
          {
            "type": "Blue",
            "name": "DoubleTime",
            "image": "./perks/Doubletime.png"
          },
          {
            "type": "Red",
            "name": "Overkill",
            "image": "./perks/Overkill.png"
          },
          {
            "type": "Yellow",
            "name": "Amped",
            "image": "./perks/Amped.png"
          }
        ],
        "utilities": [
          {
            "type": "Lethal",
            "name": "Frag Grenade",
            "image": "./utilities/frag_grenade.png"
          },
          {
            "type": "Tactical",
            "name": "Heartbeat Sensor",
            "image": "./utilities/heartbeat_sensor.png"
          }
        ]
      }
    }
  ]
}